in_azure/__init__.py
in_azure/funcs.py
tests/__init__.py
tests/test_funcs.py
create_lib_azure-0.1.0.dist-info/METADATA
create_lib_azure-0.1.0.dist-info/WHEEL
create_lib_azure-0.1.0.dist-info/top_level.txt
create_lib_azure-0.1.0.dist-info/RECORD
