Metadata-Version: 2.1
Name: create-lib-azure
Version: 0.1.0
Summary: Azure Python library
Author: Infinity Team
